mmseg/__init__.py
mmseg/version.py
mmseg/.mim/model-index.yml
mmseg/.mim/configs/_base_/default_runtime.py
mmseg/.mim/configs/_base_/datasets/ade20k.py
mmseg/.mim/configs/_base_/datasets/ade20k_640x640.py
mmseg/.mim/configs/_base_/datasets/bdd100k.py
mmseg/.mim/configs/_base_/datasets/chase_db1.py
mmseg/.mim/configs/_base_/datasets/cityscapes.py
mmseg/.mim/configs/_base_/datasets/cityscapes_1024x1024.py
mmseg/.mim/configs/_base_/datasets/cityscapes_768x768.py
mmseg/.mim/configs/_base_/datasets/cityscapes_769x769.py
mmseg/.mim/configs/_base_/datasets/cityscapes_832x832.py
mmseg/.mim/configs/_base_/datasets/coco-stuff10k.py
mmseg/.mim/configs/_base_/datasets/coco-stuff164k.py
mmseg/.mim/configs/_base_/datasets/drive.py
mmseg/.mim/configs/_base_/datasets/hrf.py
mmseg/.mim/configs/_base_/datasets/hsi_drive.py
mmseg/.mim/configs/_base_/datasets/isaid.py
mmseg/.mim/configs/_base_/datasets/levir_256x256.py
mmseg/.mim/configs/_base_/datasets/loveda.py
mmseg/.mim/configs/_base_/datasets/mapillary_v1.py
mmseg/.mim/configs/_base_/datasets/mapillary_v1_65.py
mmseg/.mim/configs/_base_/datasets/mapillary_v2.py
mmseg/.mim/configs/_base_/datasets/nyu.py
mmseg/.mim/configs/_base_/datasets/nyu_512x512.py
mmseg/.mim/configs/_base_/datasets/pascal_context.py
mmseg/.mim/configs/_base_/datasets/pascal_context_59.py
mmseg/.mim/configs/_base_/datasets/pascal_voc12.py
mmseg/.mim/configs/_base_/datasets/pascal_voc12_aug.py
mmseg/.mim/configs/_base_/datasets/potsdam.py
mmseg/.mim/configs/_base_/datasets/refuge.py
mmseg/.mim/configs/_base_/datasets/stare.py
mmseg/.mim/configs/_base_/datasets/synapse.py
mmseg/.mim/configs/_base_/datasets/vaihingen.py
mmseg/.mim/configs/_base_/models/ann_r50-d8.py
mmseg/.mim/configs/_base_/models/apcnet_r50-d8.py
mmseg/.mim/configs/_base_/models/bisenetv1_r18-d32.py
mmseg/.mim/configs/_base_/models/bisenetv2.py
mmseg/.mim/configs/_base_/models/ccnet_r50-d8.py
mmseg/.mim/configs/_base_/models/cgnet.py
mmseg/.mim/configs/_base_/models/danet_r50-d8.py
mmsegmentation_building-1.2.2.3.dist-info/LICENSE
mmsegmentation_building-1.2.2.3.dist-info/METADATA
mmsegmentation_building-1.2.2.3.dist-info/WHEEL
mmsegmentation_building-1.2.2.3.dist-info/top_level.txt
mmsegmentation_building-1.2.2.3.dist-info/RECORD
